{
  "resume_id": "RES002",
  "resume_text": "NAME: Bob Johnson\nEMAIL: bob.johnson@email.com\nPHONE: (555) 987-6543\n\nSUMMARY:\nExperienced Data Scientist with 7 years of experience in developing machine learning models and conducting data analysis. Proven ability to extract insights from complex datasets and communicate findings effectively.\n\nSKILLS:\nPython, TensorFlow, scikit-learn, Pandas, NumPy, SQL, Tableau, AWS\n\nEXPERIENCE:\nData Insights Corp. - Data Scientist (2018 - Present)\n- Developed and deployed machine learning models for predictive analytics.\n- Conducted data analysis to identify trends and patterns in customer behavior.\n\nAnalytics Solutions LLC - Data Analyst (2016 - 2018)\n- Performed data cleaning, preprocessing, and exploratory data analysis.\n- Created visualizations and reports to communicate data insights to stakeholders.\n\nEDUCATION:\nStanford University - Master's in Statistics (2016)\n\nCERTIFICATIONS:\nAWS Certified Solutions Architect",
  "extracted_skills": [
    "Python",
    "TensorFlow",
    "scikit-learn",
    "Pandas",
    "NumPy",
    "SQL",
    "Tableau",
    "AWS"
  ],
  "experience_years": 7,
  "education_level": "Master's",
  "job_history": [
    "Data Scientist",
    "Data Analyst"
  ],
  "certifications": [
    "AWS Certified Solutions Architect"
  ]
}